Workbook

Sheet Business Problem
A1: LOAN PORTFOLIO ANALYTICS — BUSINESS PROBLEM STATEMENT
A2: Prepared by: Benard Musyoka Mwinzi | benadata.github.io | Nairobi, Kenya
B4: CONTEXT
B5: Microfinance institutions (MFIs) in Kenya disburse thousands of loans annually to smallholder farmers, traders, and micro-entrepreneurs across all 47 counties. Despite strong disbursement volumes, many MFIs lack real-time visibility into portfolio health — resulting in reactive rather than proactive credit risk management.
B7: BUSINESS PROBLEM
B8: Without a structured portfolio monitoring system, credit managers cannot: 1. Identify which loan officers or counties are generating disproportionate non-performing loans (NPLs). 2. Track Portfolio-at-Risk (PAR) aging in real time, leading to delayed provisioning decisions. 3. Assess sector concentration risk before it becomes systemic. 4. Evaluate individual loan officer performance objectively. 5. Produce regulatory-ready portfolio reports for the Central Bank of Kenya (CBK) and IRA Kenya.
B10: OBJECTIVE
B11: This dashboard was designed to solve those gaps by providing: • A structured loan book with 50 loan records across 8 Kenyan counties and 8 sectors. • Automated KPI cards: Gross Portfolio, Outstanding Balance, PAR > 30 Days, Active/Delinquent counts. • Sector, county, risk grade, and PAR aging breakdowns — all driven by live Excel formulae. • Loan Officer performance scorecard with PAR rate and performance flags. • Visual charts for stakeholder presentations and board reporting.
B13: ANALYTICAL APPROACH
B14: The project follows a structured credit analysis methodology: Step 1 — Data Architecture: Design a normalized loan book with realistic Kenyan microfinance data. Step 2 — KPI Framework: Define industry-standard metrics (PAR30, PAR90, Write-Off Rate, Yield). Step 3 — Segmentation Analysis: Break down portfolio by sector, geography, risk grade, and officer. Step 4 — PAR Aging: Classify all delinquent loans into regulatory aging buckets (0/1-30/31-60/61-90/>90). Step 5 — Visualization: Present findings through charts suitable for credit committee reporting.
B16: EXPECTED OUTCOME
B17: Credit managers using this dashboard can: • Reduce NPL ratios by flagging delinquency trends before they breach provisioning thresholds. • Reallocate loan officer portfolios based on PAR performance data. • Make sector concentration decisions informed by outstanding balance distribution. • Submit accurate CBK portfolio quality reports with minimal manual effort. • Present board-ready visuals without requiring additional BI tools.

Sheet Loan Book
A1: Loan ID | B1: Borrower Name | C1: County | D1: Sector | E1: Product Type | F1: Loan Amount (KES) | G1: Disbursement Date | H1: Maturity Date | I1: Tenor (Months) | J1: Interest Rate (%) | K1: Monthly Installment (KES) | L1: Outstanding Balance (KES) | M1: Days Past Due | N1: Status | O1: Risk Grade | P1: Loan Officer | Q1: Collateral Type | R1: Collateral Value (KES)
A2: LN-2023-1001 | B2: Florence Odhiambo | C2: Nairobi | D2: Agriculture | E2: Business Loan | F2: 100000 | G2: 21-Aug-2023 | H2: 17-Feb-2024 | I2: 6 | J2: 0.235 | K2: 17827.49 | L2: 0 | M2: 0 | N2: Closed | O2: C | P2: J. Kariuki | Q2: Land Title | R2: 231000
A3: LN-2023-1002 | B3: Josephine Chelimo | C3: Mombasa | D3: Trade & Commerce | E3: Emergency Loan | F3: 200000 | G3: 12-May-2024 | H3: 27-Apr-2027 | I3: 36 | J3: 0.216 | K3: 7596.77 | L3: 0 | M3: 0 | N3: Closed | O3: B | P3: M. Otieno | Q3: Logbook | R3: 352000
A4: LN-2023-1003 | B4: Agnes Kiptoo | C4: Kisumu | D4: Manufacturing | E4: Asset Finance | F4: 75000 | G4: 21-Mar-2024 | H4: 12-Sep-2025 | I4: 18 | J4: 0.224 | K4: 4944.2 | L4: 20000 | M4: 0 | N4: Active | O4: B | P4: A. Wanjiku | Q4: Shares | R4: 132000
A5: LN-2023-1004 | B5: Helen Owino | C5: Nakuru | D5: Education | E5: Group Loan | F5: 250000 | G5: 26-Jan-2024 | H5: 20-Jan-2025 | I5: 12 | J5: 0.194 | K5: 23086.9 | L5: 138000 | M5: 0 | N5: Active | O5: B | P5: P. Kimani | Q5: Salary Undertaking | R5: 542000
A6: LN-2023-1005 | B6: David Kipchoge | C6: Eldoret | D6: Health | E6: Agricultural Loan | F6: 50000 | G6: 03-Nov-2023 | H6: 26-Apr-2025 | I6: 18 | J6: 0.189 | K6: 3211.78 | L6: 20000 | M6: 0 | N6: Active | O6: B | P6: S. Mutua | Q6: Group Guarantee | R6: 58000
A7: LN-2023-1006 | B7: Eunice Nduta | C7: Machakos | D7: Real Estate | E7: Business Loan | F7: 200000 | G7: 03-May-2023 | H7: 30-Oct-2023 | I7: 6 | J7: 0.164 | K7: 34945.81 | L7: 35000 | M7: 321 | N7: Delinquent | O7: B | P7: L. Odhiambo | Q7: Machinery | R7: 484000
A8: LN-2023-1007 | B8: James Gitau | C8: Nyeri | D8: Transport | E8: Emergency Loan | F8: 400000 | G8: 22-Feb-2024 | H8: 20-Aug-2024 | I8: 6 | J8: 0.238 | K8: 71370.16 | L8: 83000 | M8: 0 | N8: Active | O8: A | P8: R. Njenga | Q8: None | R8: 720000
A9: LN-2023-1008 | B9: Beatrice Chebet | C9: Meru | D9: Personal | E9: Asset Finance | F9: 1000000 | G9: 01-Sep-2023 | H9: 16-Aug-2026 | I9: 36 | J9: 0.157 | K9: 35009.1 | L9: 616000 | M9: 0 | N9: Active | O9: C | P9: T. Chelimo | Q9: Land Title | R9: 1792000
A10: LN-2023-1009 | B10: Esther Makena | C10: Nairobi | D10: Agriculture | E10: Group Loan | F10: 150000 | G10: 20-Apr-2024 | H10: 05-Apr-2027 | I10: 36 | J10: 0.216 | K10: 5697.57 | L10: 106000 | M10: 0 | N10: Active | O10: C | P10: J. Kariuki | Q10: Logbook | R10: 305000
A11: LN-2023-1010 | B11: Stephen Mburu | C11: Mombasa | D11: Trade & Commerce | E11: Agricultural Loan | F11: 300000 | G11: 10-Dec-2023 | H11: 02-Jun-2025 | I11: 18 | J11: 0.184 | K11: 19198.99 | L11: 61000 | M11: 0 | N11: Active | O11: A | P11: M. Otieno | Q11: Shares | R11: 533000
A12: LN-2023-1011 | B12: Priscilla Nyambura | C12: Kisumu | D12: Manufacturing | E12: Business Loan | F12: 150000 | G12: 02-Feb-2023 | H12: 26-Jul-2024 | I12: 18 | J12: 0.142 | K12: 9301.34 | L12: 43000 | M12: 314 | N12: Delinquent | O12: C | P12: A. Wanjiku | Q12: Salary Undertaking | R12: 202000
A13: LN-2023-1012 | B13: Caroline Adhiambo | C13: Nakuru | D13: Education | E13: Emergency Loan | F13: 75000 | G13: 29-Dec-2023 | H13: 26-Jun-2024 | I13: 6 | J13: 0.163 | K13: 13100.95 | L13: 62000 | M13: 0 | N13: Active | O13: C | P13: P. Kimani | Q13: Group Guarantee | R13: 177000
... A51: LN-2023-1050 | B51: Isaac Omondi | C51: Mombasa | D51: Trade & Commerce | E51: Agricultural Loan | F51: 200000 | G51: 20-Jan-2023 | H51: 19-Jul-2023 | I51: 6 | J51: 0.2 | K51: 35304.56 | L51: 73000 | M51: 207 | N51: Delinquent | O51: B | P51: M. Otieno | Q51: Land Title | R51: 419000

Sheet Portfolio Summary
A1: PORTFOLIO SUMMARY — SEGMENT ANALYSIS
A2: All figures in KES | Formulae auto-update when Loan Book data changes
B4: TABLE A — Portfolio by Sector | G4: TABLE C — Portfolio by Risk Grade
B5: Sector | C5: No. of Loans | D5: Outstanding (KES) | E5: % of Portfolio | G5: Risk Grade | H5: Count | I5: Outstanding (KES) | J5: % of Portfolio
B6: Agriculture | C6: =COUNTIF('Loan Book'!D2:D51,B6) -> 7 | D6: =SUMIF('Loan Book'!D2:D51,B6,'Loan Book'!L2:L51) -> 353000 | E6: =IFERROR(D6/SUM(D6:D13),0) -> 0.05964853 | G6: A | H6: =COUNTIF('Loan Book'!O2:O51,G6) -> 8 | I6: =SUMIF('Loan Book'!O2:O51,G6,'Loan Book'!L2:L51) -> 1041000 | J6: =IFERROR(I6/SUM(I6:I10),0) -> 0.17590402
B7: Trade & Commerce | C7: =COUNTIF('Loan Book'!D2:D51,B7) -> 7 | D7: =SUMIF('Loan Book'!D2:D51,B7,'Loan Book'!L2:L51) -> 461000 | E7: =IFERROR(D7/SUM(D6:D13),0) -> 0.077897938 | G7: B | H7: =COUNTIF('Loan Book'!O2:O51,G7) -> 12 | I7: =SUMIF('Loan Book'!O2:O51,G7,'Loan Book'!L2:L51) -> 1117000 | J7: =IFERROR(I7/SUM(I6:I10),0) -> 0.1887462
B8: Manufacturing | C8: =COUNTIF('Loan Book'!D2:D51,B8) -> 6 | D8: =SUMIF('Loan Book'!D2:D51,B8,'Loan Book'!L2:L51) -> 1200000 | E8: =IFERROR(D8/SUM(D6:D13),0) -> 0.20277121 | G8: C | H8: =COUNTIF('Loan Book'!O2:O51,G8) -> 15 | I8: =SUMIF('Loan Book'!O2:O51,G8,'Loan Book'!L2:L51) -> 2235000 | J8: =IFERROR(I8/SUM(I6:I10),0) -> 0.37766137
B9: Education | C9: =COUNTIF('Loan Book'!D2:D51,B9) -> 6 | D9: =SUMIF('Loan Book'!D2:D51,B9,'Loan Book'!L2:L51) -> 330000 | E9: =IFERROR(D9/SUM(D6:D13),0) -> 0.055762082 | G9: D | H9: =COUNTIF('Loan Book'!O2:O51,G9) -> 10 | I9: =SUMIF('Loan Book'!O2:O51,G9,'Loan Book'!L2:L51) -> 1059000 | J9: =IFERROR(I9/SUM(I6:I10),0) -> 0.17894559
B10: Health | C10: =COUNTIF('Loan Book'!D2:D51,B10) -> 6 | D10: =SUMIF('Loan Book'!D2:D51,B10,'Loan Book'!L2:L51) -> 530000 | E10: =IFERROR(D10/SUM(D6:D13),0) -> 0.089557283 | G10: E | H10: =COUNTIF('Loan Book'!O2:O51,G10) -> 5 | I10: =SUMIF('Loan Book'!O2:O51,G10,'Loan Book'!L2:L51) -> 466000 | J10: =IFERROR(I10/SUM(I6:I10),0) -> 0.078742819
B11: Real Estate | C11: =COUNTIF('Loan Book'!D2:D51,B11) -> 6 | D11: =SUMIF('Loan Book'!D2:D51,B11,'Loan Book'!L2:L51) -> 1256000 | E11: =IFERROR(D11/SUM(D6:D13),0) -> 0.21223386 | G11: TOTAL | H11: =SUM(H6:H10) -> 50 | I11: =SUM(I6:I10) -> 5918000 | J11: =SUM(J6:J10) -> 1
B12: Transport | C12: =COUNTIF('Loan Book'!D2:D51,B12) -> 6 | D12: =SUMIF('Loan Book'!D2:D51,B12,'Loan Book'!L2:L51) -> 435000 | E12: =IFERROR(D12/SUM(D6:D13),0) -> 0.073504562
B13: Personal | C13: =COUNTIF('Loan Book'!D2:D51,B13) -> 6 | D13: =SUMIF('Loan Book'!D2:D51,B13,'Loan Book'!L2:L51) -> 1353000 | E13: =IFERROR(D13/SUM(D6:D13),0) -> 0.22862454 | G13: TABLE D — PAR Aging Analysis
B14: TOTAL | C14: =SUM(C6:C13) -> 50 | D14: =SUM(D6:D13) -> 5918000 | E14: =SUM(E6:E13) -> 1 | G14: Aging Bucket | H14: Count | I14: Outstanding (KES) | J14: % of Total O/S
G15: Current (0 DPD) | H15: =COUNTIF('Loan Book'!M2:M51,0) -> 32 | I15: =SUMIF('Loan Book'!M2:M51,0,'Loan Book'!L2:L51) -> 3284000 | J15: =IFERROR(I15/SUM(I15:I19),0) -> 0.5549172
B16: TABLE B — Portfolio by County | G16: 1 – 30 DPD | H16: =COUNTIFS('Loan Book'!M2:M51,">0",'Loan Book'!M2:M51,"<=30") -> 0 | I16: =SUMPRODUCT(('Loan Book'!M2:M51>0)*('Loan Book'!M2:M51<=30)*'Loan Book'!L2:L51) -> 0 | J16: =IFERROR(I16/SUM(I15:I19),0) -> 0
B17: County | C17: No. of Loans | D17: Outstanding (KES) | E17: % of Portfolio | G17: 31 – 60 DPD | H17: =COUNTIFS('Loan Book'!M2:M51,">30",'Loan Book'!M2:M51,"<=60") -> 0 | I17: =SUMPRODUCT(('Loan Book'!M2:M51>30)*('Loan Book'!M2:M51<=60)*'Loan Book'!L2:L51) -> 0 | J17: =IFERROR(I17/SUM(I15:I19),0) -> 0
B18: Nairobi | C18: =COUNTIF('Loan Book'!C2:C51,B18) -> 7 | D18: =SUMIF('Loan Book'!C2:C51,B18,'Loan Book'!L2:L51) -> 353000 | E18: =IFERROR(D18/SUM(D18:D25),0) -> 0.15059721 | G18: 61 – 90 DPD | H18: =COUNTIFS('Loan Book'!M2:M51,">60",'Loan Book'!M2:M51,"<=90") -> 2 | I18: =SUMPRODUCT(('Loan Book'!M2:M51>60)*('Loan Book'!M2:M51<=90)*'Loan Book'!L2:L51) -> 120000 | J18: =IFERROR(I18/SUM(I15:I19),0) -> 0.020277121
B19: Mombasa | C19: =COUNTIF('Loan Book'!C2:C51,B19) -> 7 | D19: =SUMIF('Loan Book'!C2:C51,B19,'Loan Book'!L2:L51) -> 461000 | E19: =IFERROR(D19/SUM(D18:D25),0) -> 0.19667228 | G19: > 90 DPD | H19: =COUNTIFS('Loan Book'!M2:M51,">90") -> 16 | I19: =SUMPRODUCT(('Loan Book'!M2:M51>90)*'Loan Book'!L2:L51) -> 2514000 | J19: =IFERROR(I19/SUM(I15:I19),0) -> 0.42480568
B20: Kisumu | C20: =COUNTIF('Loan Book'!C2:C51,B20) -> 6 | D20: =SUMIF('Loan Book'!C2:C51,B20,'Loan Book'!L2:L51) -> 1200000 | E20: =IFERROR(D20/SUM(D18:D25),0) -> 0.5119452 | G20: TOTAL | H20: =SUM(H15:H19) -> 50 | I20: =SUM(I15:I19) -> 5918000 | J20: =SUM(J15:J19) -> 1
B21: Nakuru | C21: =COUNTIF('Loan Book'!C2:C51,B21) -> 6 | D21: =SUMIF('Loan Book'!C2:C51,B21,'Loan Book'!L2:L51) -> 330000 | E21: =IFERROR(D21/SUM(D18:D25),0) -> 0.14078493
B22: TABLE E — Portfolio KPI Scorecard
B23: KPI Metric | C23: Formula / Logic | D23: Value | E23: CBK Benchmark
B24: PAR > 30 Days | C24: Outstanding DPD>30 / Total Outstanding | D24: {=IFERROR(SUMPRODUCT(('Loan Book'!M2:M51>30)*'Loan Book'!L2:L51)/SUM('Loan Book'!L2:L51),0)} -> 0.4450828 | E24: < 5%
B25: PAR > 90 Days | C25: Outstanding DPD>90 / Total Outstanding | D25: =IFERROR(SUMPRODUCT(('Loan Book'!M2:M51>90)*'Loan Book'!L2:L51)/SUM('Loan Book'!L2:L51),0) -> 0.42480568 | E25: < 2%
B26: Write-Off Rate | C26: Written Off Loans / Total Loans | D26: =IFERROR(COUNTIF('Loan Book'!N2:N51,"Written Off")/COUNTA('Loan Book'!A2:A51),0) -> 0.08 | E26: < 2%
B27: Delinquency Rate | C27: Delinquent Loans / Total Loans | D27: =IFERROR(COUNTIF('Loan Book'!N2:N51,"Delinquent")/COUNTA('Loan Book'!A2:A51),0) -> 0.28 | E27: < 10%
B28: Portfolio Yield | C28: Avg. Interest Rate (weighted by loan amount) | D28: =IFERROR(SUMPRODUCT('Loan Book'!F2:F51,'Loan Book'!J2:J51)/SUM('Loan Book'!F2:F51),0) -> 0.18555686 | E28: ≥ 18%
B29: Repayment Rate | C29: Closed Loans / Total Loans | D29: =IFERROR(COUNTIF('Loan Book'!N2:N51,"Closed")/COUNTA('Loan Book'!A2:A51),0) -> 0.2 | E29: > 80%

Sheet Officer Performance
A1: LOAN OFFICER PERFORMANCE SCORECARD
A2: PAR Rate = DPD>30 Outstanding for Officer / Total Outstanding for Officer
B3: OFFICER PERFORMANCE — ALL LOAN OFFICERS
B4: Loan Officer | C4: Loans Disbursed | D4: Gross Portfolio (KES) | E4: Outstanding (KES) | F4: Delinquent Loans | G4: PAR Rate (%) | H4: Performance Rating
B5: J. Kariuki | C5: =COUNTIF('Loan Book'!P2:P51,B5) -> 7 | D5: =SUMIF('Loan Book'!P2:P51,B5,'Loan Book'!F2:F51) -> 1475000 | E5: =SUMIF('Loan Book'!P2:P51,B5,'Loan Book'!L2:L51) -> 353000 | F5: =COUNTIFS('Loan Book'!P2:P51,B5,'Loan Book'!N2:N51,"Delinquent") -> 1 | G5: {=IFERROR(SUMPRODUCT(('Loan Book'!P2:P51=B5)*('Loan Book'!M2:M51>30)*'Loan Book'!L2:L51)/E5,0)} -> 0.2776204 | H5: =IF(G5<0.05,"Excellent",IF(G5<0.1,"Good",IF(G5<0.2,"Needs Improvement","Critical"))) -> Critical
B6: M. Otieno | C6: =COUNTIF('Loan Book'!P2:P51,B6) -> 7 | D6: =SUMIF('Loan Book'!P2:P51,B6,'Loan Book'!F2:F51) -> 1450000 | E6: =SUMIF('Loan Book'!P2:P51,B6,'Loan Book'!L2:L51) -> 461000 | F6: =COUNTIFS('Loan Book'!P2:P51,B6,'Loan Book'!N2:N51,"Delinquent") -> 2 | G6: =IFERROR(SUMPRODUCT(('Loan Book'!P2:P51=B6)*('Loan Book'!M2:M51>30)*'Loan Book'!L2:L51)/E6,0) -> 0.37527115 | H6: =IF(G6<0.05,"Excellent",IF(G6<0.1,"Good",IF(G6<0.2,"Needs Improvement","Critical"))) -> Critical
B7: A. Wanjiku | C7: =COUNTIF('Loan Book'!P2:P51,B7) -> 6 | D7: =SUMIF('Loan Book'!P2:P51,B7,'Loan Book'!F2:F51) -> 2175000 | E7: =SUMIF('Loan Book'!P2:P51,B7,'Loan Book'!L2:L51) -> 1200000 | F7: =COUNTIFS('Loan Book'!P2:P51,B7,'Loan Book'!N2:N51,"Delinquent") -> 2 | G7: =IFERROR(SUMPRODUCT(('Loan Book'!P2:P51=B7)*('Loan Book'!M2:M51>30)*'Loan Book'!L2:L51)/E7,0) -> 0.7525 | H7: =IF(G7<0.05,"Excellent",IF(G7<0.1,"Good",IF(G7<0.2,"Needs Improvement","Critical"))) -> Critical
B8: P. Kimani | C8: =COUNTIF('Loan Book'!P2:P51,B8) -> 6 | D8: =SUMIF('Loan Book'!P2:P51,B8,'Loan Book'!F2:F51) -> 1000000 | E8: =SUMIF('Loan Book'!P2:P51,B8,'Loan Book'!L2:L51) -> 330000 | F8: =COUNTIFS('Loan Book'!P2:P51,B8,'Loan Book'!N2:N51,"Delinquent") -> 1 | G8: =IFERROR(SUMPRODUCT(('Loan Book'!P2:P51=B8)*('Loan Book'!M2:M51>30)*'Loan Book'!L2:L51)/E8,0) -> 0.39393939 | H8: =IF(G8<0.05,"Excellent",IF(G8<0.1,"Good",IF(G8<0.2,"Needs Improvement","Critical"))) -> Critical
B9: S. Mutua | C9: =COUNTIF('Loan Book'!P2:P51,B9) -> 6 | D9: =SUMIF('Loan Book'!P2:P51,B9,'Loan Book'!F2:F51) -> 1125000 | E9: =SUMIF('Loan Book'!P2:P51,B9,'Loan Book'!L2:L51) -> 530000 | F9: =COUNTIFS('Loan Book'!P2:P51,B9,'Loan Book'!N2:N51,"Delinquent") -> 1 | G9: =IFERROR(SUMPRODUCT(('Loan Book'!P2:P51=B9)*('Loan Book'!M2:M51>30)*'Loan Book'!L2:L51)/E9,0) -> 0.071698113 | H9: =IF(G9<0.05,"Excellent",IF(G9<0.1,"Good",IF(G9<0.2,"Needs Improvement","Critical"))) -> Good
B10: L. Odhiambo | C10: =COUNTIF('Loan Book'!P2:P51,B10) -> 6 | D10: =SUMIF('Loan Book'!P2:P51,B10,'Loan Book'!F2:F51) -> 1725000 | E10: =SUMIF('Loan Book'!P2:P51,B10,'Loan Book'!L2:L51) -> 1256000 | F10: =COUNTIFS('Loan Book'!P2:P51,B10,'Loan Book'!N2:N51,"Delinquent") -> 4 | G10: =IFERROR(SUMPRODUCT(('Loan Book'!P2:P51=B10)*('Loan Book'!M2:M51>30)*'Loan Book'!L2:L51)/E10,0) -> 0.39649682 | H10: =IF(G10<0.05,"Excellent",IF(G10<0.1,"Good",IF(G10<0.2,"Needs Improvement","Critical"))) -> Critical
B11: R. Njenga | C11: =COUNTIF('Loan Book'!P2:P51,B11) -> 6 | D11: =SUMIF('Loan Book'!P2:P51,B11,'Loan Book'!F2:F51) -> 1875000 | E11: =SUMIF('Loan Book'!P2:P51,B11,'Loan Book'!L2:L51) -> 435000 | F11: =COUNTIFS('Loan Book'!P2:P51,B11,'Loan Book'!N2:N51,"Delinquent") -> 1 | G11: =IFERROR(SUMPRODUCT(('Loan Book'!P2:P51=B11)*('Loan Book'!M2:M51>30)*'Loan Book'!L2:L51)/E11,0) -> 0.34482759 | H11: =IF(G11<0.05,"Excellent",IF(G11<0.1,"Good",IF(G11<0.2,"Needs Improvement","Critical"))) -> Critical
B12: T. Chelimo | C12: =COUNTIF('Loan Book'!P2:P51,B12) -> 6 | D12: =SUMIF('Loan Book'!P2:P51,B12,'Loan Book'!F2:F51) -> 1925000 | E12: =SUMIF('Loan Book'!P2:P51,B12,'Loan Book'!L2:L51) -> 1353000 | F12: =COUNTIFS('Loan Book'!P2:P51,B12,'Loan Book'!N2:N51,"Delinquent") -> 2 | G12: =IFERROR(SUMPRODUCT(('Loan Book'!P2:P51=B12)*('Loan Book'!M2:M51>30)*'Loan Book'!L2:L51)/E12,0) -> 0.47597931 | H12: =IF(G12<0.05,"Excellent",IF(G12<0.1,"Good",IF(G12<0.2,"Needs Improvement","Critical"))) -> Critical
B13: PORTFOLIO TOTAL | C13: =SUM(C5:C12) -> 50 | D13: =SUM(D5:D12) -> 12750000 | E13: =SUM(E5:E12) -> 5918000 | F13: =SUM(F5:F12) -> 14 | G13: =IFERROR(SUMPRODUCT(('Loan Book'!M2:M51>30)*'Loan Book'!L2:L51)/SUM('Loan Book'!L2:L51),0) -> 0.4450828
B15: PERFORMANCE RATING LEGEND
B16: Excellent | C16: PAR < 5%
B17: Good | C17: PAR 5% – 9.9%
B18: Needs Improvement | C18: PAR 10% – 19.9%
B19: Critical | C19: PAR ≥ 20%

Sheet Executive Summary
A1: EXECUTIVE SUMMARY — LOAN PORTFOLIO PERFORMANCE
A2: Reporting Period: FY 2023–2024 | Portfolio Date: 31-Dec-2024 | Currency: KES (Kenyan Shilling)
B4: KEY PERFORMANCE INDICATORS
B5: Total Loans in Portfolio | C5: =COUNTA('Loan Book'!A2:A51) -> 50
B6: Gross Loan Book (KES) | C6: =SUM('Loan Book'!F2:F51) -> 12750000
B7: Total Outstanding (KES) | C7: =SUM('Loan Book'!L2:L51) -> 5918000
B8: Active Loans | C8: =COUNTIF('Loan Book'!N2:N51,"Active") -> 22
B9: Delinquent Loans | C9: =COUNTIF('Loan Book'!N2:N51,"Delinquent") -> 14
B10: Written Off Loans | C10: =COUNTIF('Loan Book'!N2:N51,"Written Off") -> 4
B11: PAR > 30 Days (%) | C11: =IFERROR(SUMPRODUCT(('Loan Book'!M2:M51>30)*'Loan Book'!L2:L51)/SUM('Loan Book'!L2:L51),0) -> 0.4450828
B12: Avg. Loan Size (KES) | C12: =IFERROR(SUM('Loan Book'!F2:F51)/COUNTA('Loan Book'!A2:A51),0) -> 255000
B13: Avg. Interest Rate | C13: =AVERAGE('Loan Book'!J2:J51) -> 0.18818
B14: No. of Loan Officers | C14: =COUNTA('Officer Performance'!A4:A11) -> 0
B15: No. of Counties Covered | C15: =COUNTA('Portfolio Summary'!A22:A29) -> 0
B16: No. of Sectors | C16: =COUNTA('Portfolio Summary'!A10:A17) -> 0
B18: PORTFOLIO HEALTH
B19: ▶ Portfolio Quality
B20: The portfolio recorded a PAR>30 rate driven by 14 delinquent accounts. Four loans have been written off, signalling early-stage credit stress concentrated in the D and E risk-grade buckets. Prompt provisioning review is recommended for all loans with Days Past Due exceeding 60 days.
B22: ▶ Sector Concentration
B23: Trade & Commerce and Agriculture collectively represent the highest outstanding balances, consistent with typical Kenyan MFI portfolios. Real Estate and Manufacturing show lower loan counts but higher average ticket sizes, elevating single-obligor concentration risk in those segments.
B25: ▶ Geographic Distribution
B26: Nairobi and Mombasa dominate the portfolio by volume, reflecting urban branch density. Machakos and Meru show emerging delinquency trends that warrant field-level credit review before further disbursements are approved in those counties.
B28: ▶ Loan Officer Performance
B29: PAR rates vary significantly across the eight loan officers. Officers with PAR rates exceeding 10% have been flagged as 'Needs Improvement' or 'Critical' in the Officer Performance sheet. Management should review their client appraisal processes and consider supervised disbursements pending improvement.
B31: ▶ Recommendations
B32: 1. Implement a 90-day early warning trigger for all loans crossing the 30 DPD bucket. 2. Cap sector exposure to Trade & Commerce at 30% of total outstanding. 3. Introduce bi-monthly portfolio review meetings for officers rated Critical. 4. Strengthen collateral documentation — 'None' collateral loans show disproportionate write-offs. 5. Expand coverage to Eldoret and Nyeri where low disbursement suggests untapped market.

Sheet Charts & Visuals
A1: CREDIT PORTFOLIO DASHBOARD
A2: Prepared by Benard Musyoka Mwinzi |Credit Analyst | Data Analyst| Google Data Analytics Certificate | https://benadata.github.io/
B4: NUMBER OF LOANS | D4: TOTAL AMOUNT | F4: AVERAGE INTEREST RATE | L4: TOP LOAN OFFICER | T4: LEAST SELLING OFFICER | Y4: HIGHEST PAR OFFICER
B5: ='Executive Summary'!C5 -> 50 | D5: ='Executive Summary'!C6 -> 12750000 | F5: ='Executive Summary'!C13 -> 0.18818 | L5: =INDEX('Officer Performance'!B5:B12,MATCH(MAX('Officer Performance'!D5:D12),'Officer Performance'!D5:D12,0)) -> A. Wanjiku | T5: =INDEX('Officer Performance'!B5:B12,MATCH(MIN('Officer Performance'!D5:D12),'Officer Performance'!D5:D12,0)) -> P. Kimani | Y5: =INDEX(B36:B43,MATCH(MAX(D36:D43),D36:D43,0)) -> A. Wanjiku
B8: Loan Distribution by Status
B9: Status | D9: Number of Loans
B10: Written Off | D10: =COUNTIF('Loan Book'!N2:N51,"Written Off") -> 4
B11: Closed | D11: =COUNTIF('Loan Book'!N2:N51,"Closed") -> 10
B12: Delinquent | D12: =COUNTIF('Loan Book'!N2:N51,"Delinquent") -> 14
B13: Active | D13: =COUNTIF('Loan Book'!N2:N51,"Active") -> 22
B15: Outstanding Amount by Sector
B16: Sector | D16: Outstanding (KES)
B17: Education | D17: =SUMIF('Loan Book'!D2:D51,"Education",'Loan Book'!L2:L51) -> 330000
B18: Agriculture | D18: =SUMIF('Loan Book'!D2:D51,"Agriculture",'Loan Book'!L2:L51) -> 353000
B19: Transport | D19: =SUMIF('Loan Book'!D2:D51,"Transport",'Loan Book'!L2:L51) -> 435000
B20: Trade & Commerce | D20: =SUMIF('Loan Book'!D2:D51,"Trade & Commerce",'Loan Book'!L2:L51) -> 461000
B21: Health | D21: =SUMIF('Loan Book'!D2:D51,"Health",'Loan Book'!L2:L51) -> 530000
B22: Manufacturing | D22: =SUMIF('Loan Book'!D2:D51,"Manufacturing",'Loan Book'!L2:L51) -> 1200000
B23: Real Estate | D23: =SUMIF('Loan Book'!D2:D51,"Real Estate",'Loan Book'!L2:L51) -> 1256000
B24: Personal | D24: =SUMIF('Loan Book'!D2:D51,"Personal",'Loan Book'!L2:L51) -> 1353000
B26: Outstanding Amount by DPD Bucket
B27: DPD Bucket | D27: Outstanding (KES)
B28: Current | D28: =SUMIF('Loan Book'!M2:M51,0,'Loan Book'!L2:L51) -> 3284000
B29: 1-30 DPD | D29: =SUMPRODUCT(('Loan Book'!M2:M51>0)*('Loan Book'!M2:M51<=30)*'Loan Book'!L2:L51) -> 0
B30: 31-60 DPD | D30: =SUMPRODUCT(('Loan Book'!M2:M51>30)*('Loan Book'!M2:M51<=60)*'Loan Book'!L2:L51) -> 0
B31: 61-90 DPD | D31: =SUMPRODUCT(('Loan Book'!M2:M51>60)*('Loan Book'!M2:M51<=90)*'Loan Book'!L2:L51) -> 120000
B32: >90 DPD | D32: =SUMPRODUCT(('Loan Book'!M2:M51>90)*'Loan Book'!L2:L51) -> 2514000
B34: PAR Rate by Loan Officer
B35: Loan Officer | D35: PAR Rate
B36: S. Mutua | D36: =IFERROR(SUMPRODUCT(('Loan Book'!P2:P51="S. Mutua")*('Loan Book'!M2:M51>30)*'Loan Book'!L2:L51)/SUMIF('Loan Book'!P2:P51,"S. Mutua",'Loan Book'!L2:L51),0) -> 0.071698113
B37: J. Kariuki | D37: {=IFERROR(SUMPRODUCT(('Loan Book'!P2:P51="J. Kariuki")*('Loan Book'!M2:M51>30)*'Loan Book'!L2:L51)/SUMIF('Loan Book'!P2:P51,"J. Kariuki",'Loan Book'!L2:L51),0)} -> 0.2776204
B38: R. Njenga | D38: =IFERROR(SUMPRODUCT(('Loan Book'!P2:P51="R. Njenga")*('Loan Book'!M2:M51>30)*'Loan Book'!L2:L51)/SUMIF('Loan Book'!P2:P51,"R. Njenga",'Loan Book'!L2:L51),0) -> 0.34482759
B39: M. Otieno | D39: =IFERROR(SUMPRODUCT(('Loan Book'!P2:P51="M. Otieno")*('Loan Book'!M2:M51>30)*'Loan Book'!L2:L51)/SUMIF('Loan Book'!P2:P51,"M. Otieno",'Loan Book'!L2:L51),0) -> 0.37527115
B40: P. Kimani | D40: =IFERROR(SUMPRODUCT(('Loan Book'!P2:P51="P. Kimani")*('Loan Book'!M2:M51>30)*'Loan Book'!L2:L51)/SUMIF('Loan Book'!P2:P51,"P. Kimani",'Loan Book'!L2:L51),0) -> 0.39393939
B41: L. Odhiambo | D41: =IFERROR(SUMPRODUCT(('Loan Book'!P2:P51="L. Odhiambo")*('Loan Book'!M2:M51>30)*'Loan Book'!L2:L51)/SUMIF('Loan Book'!P2:P51,"L. Odhiambo",'Loan Book'!L2:L51),0) -> 0.39649682
B42: T. Chelimo | D42: =IFERROR(SUMPRODUCT(('Loan Book'!P2:P51="T. Chelimo")*('Loan Book'!M2:M51>30)*'Loan Book'!L2:L51)/SUMIF('Loan Book'!P2:P51,"T. Chelimo",'Loan Book'!L2:L51),0) -> 0.47597931
B43: A. Wanjiku | D43: =IFERROR(SUMPRODUCT(('Loan Book'!P2:P51="A. Wanjiku")*('Loan Book'!M2:M51>30)*'Loan Book'!L2:L51)/SUMIF('Loan Book'!P2:P51,"A. Wanjiku",'Loan Book'!L2:L51),0) -> 0.7525
